fastapi_better_di/__init__.py
fastapi_better_di/_utils.py
fastapi_better_di/exceptions.py
fastapi_better_di/patcher/__init__.py
fastapi_better_di/patcher/_utils.py
fastapi_better_di/patcher/auto.py
fastapi_better_di/patcher/manual.py
fastapi_better_di-0.3.4.dist-info/METADATA
fastapi_better_di-0.3.4.dist-info/WHEEL
fastapi_better_di-0.3.4.dist-info/top_level.txt
fastapi_better_di-0.3.4.dist-info/RECORD
