Metadata-Version: 2.1
Name: fastapi-better-di
Version: 0.3.4
Home-page: https://github.com/MaximZayats/fastapi-better-di
Author: Maxim
Author-email: maximzayats1@gmail.com
Keywords: python,fastapi,di,dependency injection,fastapi di
Requires-Dist: fastapi (<0.86.1)
